picycle/__init__.py
picycle/__main__.py
picycle/epicycle.py
photoepicycle-0.1.2.dist-info/LICENSE
photoepicycle-0.1.2.dist-info/METADATA
photoepicycle-0.1.2.dist-info/WHEEL
photoepicycle-0.1.2.dist-info/top_level.txt
photoepicycle-0.1.2.dist-info/RECORD
