Metadata-Version: 2.1
Name: photoepicycle
Version: 0.1.2
Summary: Fourier epicycle library
Home-page: https://github.com/abinmahfuth/Picycle
Author: Abdulrahman Binmahfuth
Author-email: a.binmahfodh@gmail.com
License: UNKNOWN
Project-URL: Bug Tracker, https://github.com/abinmahfuth/Picycle/issues
Platform: UNKNOWN
Classifier: Programming Language :: Python :: 3
Classifier: License :: OSI Approved :: MIT License
Classifier: Operating System :: OS Independent
Requires-Python: >=3.6
License-File: LICENSE
Requires-Dist: matplotlib
Requires-Dist: numpy
Requires-Dist: scikit-image
Requires-Dist: opencv-python
Requires-Dist: scikit-learn
Requires-Dist: tqdm
